fcio/__init__.py
fcio/fcio.cpython-311-x86_64-linux-gnu.so
fcio-0.9.1.dist-info/METADATA
fcio-0.9.1.dist-info/WHEEL
fcio-0.9.1.dist-info/RECORD
