Metadata-Version: 2.1
Name: fcio
Version: 0.9.1
Summary: FlashCam File Format (FCIO) reader for python.
Author-Email: Simon Sailer <simon.sailer@mpi-hd.mpg.de>
License: MPL-2.0
Classifier: Development Status :: 4 - Beta
Classifier: Environment :: Console
Classifier: Intended Audience :: Developers
Classifier: Intended Audience :: Information Technology
Classifier: Intended Audience :: Science/Research
Classifier: License :: OSI Approved :: Mozilla Public License 2.0 (MPL 2.0)
Classifier: Operating System :: MacOS
Classifier: Operating System :: POSIX
Classifier: Operating System :: Unix
Classifier: Programming Language :: C
Classifier: Programming Language :: Python
Classifier: Programming Language :: Python :: 3 :: Only
Classifier: Topic :: Scientific/Engineering
Classifier: Topic :: Scientific/Engineering :: Information Analysis
Classifier: Topic :: Scientific/Engineering :: Mathematics
Classifier: Topic :: Scientific/Engineering :: Physics
Project-URL: Homepage, https://github.com/FlashCam/fcio-py
Project-URL: Repository, https://github.com/FlashCam/fcio-py.git
Project-URL: Issues, https://github.com/FlashCam/fcio-py/issues
Project-URL: Changelog, https://github.com/FlashCam/fcio-py/blob/main/CHANGELOG.md
Project-URL: Documentation, https://flashcam.github.io/fcio-py/
Requires-Python: >=3.8
Requires-Dist: numpy>=1.23.5
